simplematrixlib/__init__.py
simplematrixlib/api.py
simplematrixlib-0.6.0.dist-info/LICENSE
simplematrixlib-0.6.0.dist-info/METADATA
simplematrixlib-0.6.0.dist-info/WHEEL
simplematrixlib-0.6.0.dist-info/top_level.txt
simplematrixlib-0.6.0.dist-info/RECORD
