Metadata-Version: 2.1
Name: simplematrixlib
Version: 0.6.0
Summary: A simple python library for using                  the matrix client-server API
Home-page: https://gitlab.com/Swedneck/simplematrixlib
Author: Tim Stahel
Author-email: simplematrixlib@swedneck.xyz
License: UNKNOWN
Platform: UNKNOWN
Classifier: Programming Language :: Python :: 3
Classifier: Topic :: Communications :: Chat
Classifier: License :: OSI Approved :: GNU Affero General Public License v3
Classifier: Operating System :: OS Independent
Requires-Python: >=3.7
Requires-Dist: configargparse
Requires-Dist: requests
